make_package_selector/__init__.py
make_package_selector/make_package_selector.py
simple_term_menu/__init__.py
simple_term_menu/simple_term_menu.py
make_package_selector-1.1.post1.dist-info/LICENSE
make_package_selector-1.1.post1.dist-info/METADATA
make_package_selector-1.1.post1.dist-info/WHEEL
make_package_selector-1.1.post1.dist-info/entry_points.txt
make_package_selector-1.1.post1.dist-info/top_level.txt
make_package_selector-1.1.post1.dist-info/RECORD
