Metadata-Version: 2.1
Name: make-package-selector
Version: 1.1.post1
Summary: A tool to select directories and run make clean all command on those selected directory/src
Home-page: https://github.com/animeshdas/make-package-selector
Author: Animesh Das
Author-email: jobs4ani@gmail.com
Classifier: Programming Language :: Python :: 3
Classifier: License :: OSI Approved :: MIT License
Classifier: Operating System :: OS Independent
Requires-Python: >=3.6
License-File: LICENSE
Requires-Dist: simple-term-menu
